test_stages/__init__.py
test_stages/cmd.py
test_stages/py.typed
test_stages/tox_stages/__init__.py
test_stages/tox_stages/__main__.py
tox_trivtags/__init__.py
tox_trivtags/parse.py
tox_trivtags/py.typed
test_stages-0.2.0.dist-info/METADATA
test_stages-0.2.0.dist-info/WHEEL
test_stages-0.2.0.dist-info/entry_points.txt
test_stages-0.2.0.dist-info/RECORD
