Metadata-Version: 2.3
Name: test_stages
Version: 0.2.0
Summary: Group Tox, Nox, etc environments into stages, run them in parallel
Project-URL: Homepage, https://devel.ringlet.net/devel/test-stages
Project-URL: Changes, https://devel.ringlet.net/devel/test-stages/changes/
Project-URL: Issue Tracker, https://gitlab.com/ppentchev/test-stages/-/issues
Project-URL: Source Code, https://gitlab.com/ppentchev/test-stages
Author-email: Peter Pentchev <roam@ringlet.net>
License: BSD-2-Clause
Classifier: Development Status :: 4 - Beta
Classifier: Environment :: Console
Classifier: Framework :: tox
Classifier: Intended Audience :: Developers
Classifier: License :: DFSG approved
Classifier: License :: Freely Distributable
Classifier: License :: OSI Approved
Classifier: License :: OSI Approved :: BSD License
Classifier: Operating System :: POSIX
Classifier: Operating System :: Unix
Classifier: Programming Language :: Python
Classifier: Programming Language :: Python :: 3
Classifier: Programming Language :: Python :: 3 :: Only
Classifier: Programming Language :: Python :: 3.10
Classifier: Programming Language :: Python :: 3.11
Classifier: Programming Language :: Python :: 3.12
Classifier: Programming Language :: Python :: 3.13
Classifier: Topic :: Software Development
Classifier: Topic :: Software Development :: Testing
Classifier: Topic :: Software Development :: Testing :: Unit
Classifier: Topic :: Utilities
Classifier: Typing :: Typed
Requires-Python: >=3.10
Requires-Dist: click<9,>=8
Requires-Dist: packaging<25,>=17
Requires-Dist: parse-stages<0.2,>=0.1.4
Requires-Dist: pyparsing<4,>=3
Requires-Dist: tomli<3,>=2; python_version < '3.11'
Requires-Dist: utf8-locale<2,>=1
Provides-Extra: tox
Requires-Dist: tox<5,>=4; extra == 'tox'
